{
  "type": "GROUP",
"name": "Global Information",
"path": "",
"pathFormatted": "group_missing-name-b06d1",
"stats": {
    "name": "Global Information",
    "numberOfRequests": {
        "total": 16,
        "ok": 16,
        "ko": 0
    },
    "minResponseTime": {
        "total": 14,
        "ok": 14,
        "ko": 0
    },
    "maxResponseTime": {
        "total": 210,
        "ok": 210,
        "ko": 0
    },
    "meanResponseTime": {
        "total": 83,
        "ok": 83,
        "ko": 0
    },
    "standardDeviation": {
        "total": 51,
        "ok": 51,
        "ko": 0
    },
    "percentiles1": {
        "total": 75,
        "ok": 75,
        "ko": 0
    },
    "percentiles2": {
        "total": 104,
        "ok": 104,
        "ko": 0
    },
    "percentiles3": {
        "total": 162,
        "ok": 162,
        "ko": 0
    },
    "percentiles4": {
        "total": 200,
        "ok": 200,
        "ko": 0
    },
    "group1": {
        "name": "t < 800 ms",
        "count": 16,
        "percentage": 100
    },
    "group2": {
        "name": "800 ms < t < 1200 ms",
        "count": 0,
        "percentage": 0
    },
    "group3": {
        "name": "t > 1200 ms",
        "count": 0,
        "percentage": 0
    },
    "group4": {
        "name": "failed",
        "count": 0,
        "percentage": 0
    },
    "meanNumberOfRequestsPerSecond": {
        "total": 8.0,
        "ok": 8.0,
        "ko": 0
    }
},
"contents": {
"req_trigger-login-8dec8": {
        "type": "REQUEST",
        "name": "Trigger login",
"path": "Trigger login",
"pathFormatted": "req_trigger-login-8dec8",
"stats": {
    "name": "Trigger login",
    "numberOfRequests": {
        "total": 1,
        "ok": 1,
        "ko": 0
    },
    "minResponseTime": {
        "total": 75,
        "ok": 75,
        "ko": 0
    },
    "maxResponseTime": {
        "total": 75,
        "ok": 75,
        "ko": 0
    },
    "meanResponseTime": {
        "total": 75,
        "ok": 75,
        "ko": 0
    },
    "standardDeviation": {
        "total": 0,
        "ok": 0,
        "ko": 0
    },
    "percentiles1": {
        "total": 75,
        "ok": 75,
        "ko": 0
    },
    "percentiles2": {
        "total": 75,
        "ok": 75,
        "ko": 0
    },
    "percentiles3": {
        "total": 75,
        "ok": 75,
        "ko": 0
    },
    "percentiles4": {
        "total": 75,
        "ok": 75,
        "ko": 0
    },
    "group1": {
        "name": "t < 800 ms",
        "count": 1,
        "percentage": 100
    },
    "group2": {
        "name": "800 ms < t < 1200 ms",
        "count": 0,
        "percentage": 0
    },
    "group3": {
        "name": "t > 1200 ms",
        "count": 0,
        "percentage": 0
    },
    "group4": {
        "name": "failed",
        "count": 0,
        "percentage": 0
    },
    "meanNumberOfRequestsPerSecond": {
        "total": 0.5,
        "ok": 0.5,
        "ko": 0
    }
}
    },"req_trigger-login-r-6c3d2": {
        "type": "REQUEST",
        "name": "Trigger login Redirect 1",
"path": "Trigger login Redirect 1",
"pathFormatted": "req_trigger-login-r-6c3d2",
"stats": {
    "name": "Trigger login Redirect 1",
    "numberOfRequests": {
        "total": 1,
        "ok": 1,
        "ko": 0
    },
    "minResponseTime": {
        "total": 14,
        "ok": 14,
        "ko": 0
    },
    "maxResponseTime": {
        "total": 14,
        "ok": 14,
        "ko": 0
    },
    "meanResponseTime": {
        "total": 14,
        "ok": 14,
        "ko": 0
    },
    "standardDeviation": {
        "total": 0,
        "ok": 0,
        "ko": 0
    },
    "percentiles1": {
        "total": 14,
        "ok": 14,
        "ko": 0
    },
    "percentiles2": {
        "total": 14,
        "ok": 14,
        "ko": 0
    },
    "percentiles3": {
        "total": 14,
        "ok": 14,
        "ko": 0
    },
    "percentiles4": {
        "total": 14,
        "ok": 14,
        "ko": 0
    },
    "group1": {
        "name": "t < 800 ms",
        "count": 1,
        "percentage": 100
    },
    "group2": {
        "name": "800 ms < t < 1200 ms",
        "count": 0,
        "percentage": 0
    },
    "group3": {
        "name": "t > 1200 ms",
        "count": 0,
        "percentage": 0
    },
    "group4": {
        "name": "failed",
        "count": 0,
        "percentage": 0
    },
    "meanNumberOfRequestsPerSecond": {
        "total": 0.5,
        "ok": 0.5,
        "ko": 0
    }
}
    },"req_trigger-login-r-8d6c2": {
        "type": "REQUEST",
        "name": "Trigger login Redirect 2",
"path": "Trigger login Redirect 2",
"pathFormatted": "req_trigger-login-r-8d6c2",
"stats": {
    "name": "Trigger login Redirect 2",
    "numberOfRequests": {
        "total": 1,
        "ok": 1,
        "ko": 0
    },
    "minResponseTime": {
        "total": 60,
        "ok": 60,
        "ko": 0
    },
    "maxResponseTime": {
        "total": 60,
        "ok": 60,
        "ko": 0
    },
    "meanResponseTime": {
        "total": 60,
        "ok": 60,
        "ko": 0
    },
    "standardDeviation": {
        "total": 0,
        "ok": 0,
        "ko": 0
    },
    "percentiles1": {
        "total": 60,
        "ok": 60,
        "ko": 0
    },
    "percentiles2": {
        "total": 60,
        "ok": 60,
        "ko": 0
    },
    "percentiles3": {
        "total": 60,
        "ok": 60,
        "ko": 0
    },
    "percentiles4": {
        "total": 60,
        "ok": 60,
        "ko": 0
    },
    "group1": {
        "name": "t < 800 ms",
        "count": 1,
        "percentage": 100
    },
    "group2": {
        "name": "800 ms < t < 1200 ms",
        "count": 0,
        "percentage": 0
    },
    "group3": {
        "name": "t > 1200 ms",
        "count": 0,
        "percentage": 0
    },
    "group4": {
        "name": "failed",
        "count": 0,
        "percentage": 0
    },
    "meanNumberOfRequestsPerSecond": {
        "total": 0.5,
        "ok": 0.5,
        "ko": 0
    }
}
    },"req_govuk-template--fe104": {
        "type": "REQUEST",
        "name": "govuk-template.css?0.19.2 Redirect 2",
"path": "govuk-template.css?0.19.2 Redirect 2",
"pathFormatted": "req_govuk-template--fe104",
"stats": {
    "name": "govuk-template.css?0.19.2 Redirect 2",
    "numberOfRequests": {
        "total": 1,
        "ok": 1,
        "ko": 0
    },
    "minResponseTime": {
        "total": 94,
        "ok": 94,
        "ko": 0
    },
    "maxResponseTime": {
        "total": 94,
        "ok": 94,
        "ko": 0
    },
    "meanResponseTime": {
        "total": 94,
        "ok": 94,
        "ko": 0
    },
    "standardDeviation": {
        "total": 0,
        "ok": 0,
        "ko": 0
    },
    "percentiles1": {
        "total": 94,
        "ok": 94,
        "ko": 0
    },
    "percentiles2": {
        "total": 94,
        "ok": 94,
        "ko": 0
    },
    "percentiles3": {
        "total": 94,
        "ok": 94,
        "ko": 0
    },
    "percentiles4": {
        "total": 94,
        "ok": 94,
        "ko": 0
    },
    "group1": {
        "name": "t < 800 ms",
        "count": 1,
        "percentage": 100
    },
    "group2": {
        "name": "800 ms < t < 1200 ms",
        "count": 0,
        "percentage": 0
    },
    "group3": {
        "name": "t > 1200 ms",
        "count": 0,
        "percentage": 0
    },
    "group4": {
        "name": "failed",
        "count": 0,
        "percentage": 0
    },
    "meanNumberOfRequestsPerSecond": {
        "total": 0.5,
        "ok": 0.5,
        "ko": 0
    }
}
    },"req_govuk-template--9ca42": {
        "type": "REQUEST",
        "name": "govuk-template-print.css?0.19.2 Redirect 2",
"path": "govuk-template-print.css?0.19.2 Redirect 2",
"pathFormatted": "req_govuk-template--9ca42",
"stats": {
    "name": "govuk-template-print.css?0.19.2 Redirect 2",
    "numberOfRequests": {
        "total": 1,
        "ok": 1,
        "ko": 0
    },
    "minResponseTime": {
        "total": 74,
        "ok": 74,
        "ko": 0
    },
    "maxResponseTime": {
        "total": 74,
        "ok": 74,
        "ko": 0
    },
    "meanResponseTime": {
        "total": 74,
        "ok": 74,
        "ko": 0
    },
    "standardDeviation": {
        "total": 0,
        "ok": 0,
        "ko": 0
    },
    "percentiles1": {
        "total": 74,
        "ok": 74,
        "ko": 0
    },
    "percentiles2": {
        "total": 74,
        "ok": 74,
        "ko": 0
    },
    "percentiles3": {
        "total": 74,
        "ok": 74,
        "ko": 0
    },
    "percentiles4": {
        "total": 74,
        "ok": 74,
        "ko": 0
    },
    "group1": {
        "name": "t < 800 ms",
        "count": 1,
        "percentage": 100
    },
    "group2": {
        "name": "800 ms < t < 1200 ms",
        "count": 0,
        "percentage": 0
    },
    "group3": {
        "name": "t > 1200 ms",
        "count": 0,
        "percentage": 0
    },
    "group4": {
        "name": "failed",
        "count": 0,
        "percentage": 0
    },
    "meanNumberOfRequestsPerSecond": {
        "total": 0.5,
        "ok": 0.5,
        "ko": 0
    }
}
    },"req_fonts-css-0-19--da889": {
        "type": "REQUEST",
        "name": "fonts.css?0.19.2 Redirect 2",
"path": "fonts.css?0.19.2 Redirect 2",
"pathFormatted": "req_fonts-css-0-19--da889",
"stats": {
    "name": "fonts.css?0.19.2 Redirect 2",
    "numberOfRequests": {
        "total": 1,
        "ok": 1,
        "ko": 0
    },
    "minResponseTime": {
        "total": 210,
        "ok": 210,
        "ko": 0
    },
    "maxResponseTime": {
        "total": 210,
        "ok": 210,
        "ko": 0
    },
    "meanResponseTime": {
        "total": 210,
        "ok": 210,
        "ko": 0
    },
    "standardDeviation": {
        "total": 0,
        "ok": 0,
        "ko": 0
    },
    "percentiles1": {
        "total": 210,
        "ok": 210,
        "ko": 0
    },
    "percentiles2": {
        "total": 210,
        "ok": 210,
        "ko": 0
    },
    "percentiles3": {
        "total": 210,
        "ok": 210,
        "ko": 0
    },
    "percentiles4": {
        "total": 210,
        "ok": 210,
        "ko": 0
    },
    "group1": {
        "name": "t < 800 ms",
        "count": 1,
        "percentage": 100
    },
    "group2": {
        "name": "800 ms < t < 1200 ms",
        "count": 0,
        "percentage": 0
    },
    "group3": {
        "name": "t > 1200 ms",
        "count": 0,
        "percentage": 0
    },
    "group4": {
        "name": "failed",
        "count": 0,
        "percentage": 0
    },
    "meanNumberOfRequestsPerSecond": {
        "total": 0.5,
        "ok": 0.5,
        "ko": 0
    }
}
    },"req_favicon-ico-0-1-8df4b": {
        "type": "REQUEST",
        "name": "favicon.ico?0.19.2 Redirect 2",
"path": "favicon.ico?0.19.2 Redirect 2",
"pathFormatted": "req_favicon-ico-0-1-8df4b",
"stats": {
    "name": "favicon.ico?0.19.2 Redirect 2",
    "numberOfRequests": {
        "total": 1,
        "ok": 1,
        "ko": 0
    },
    "minResponseTime": {
        "total": 91,
        "ok": 91,
        "ko": 0
    },
    "maxResponseTime": {
        "total": 91,
        "ok": 91,
        "ko": 0
    },
    "meanResponseTime": {
        "total": 91,
        "ok": 91,
        "ko": 0
    },
    "standardDeviation": {
        "total": 0,
        "ok": 0,
        "ko": 0
    },
    "percentiles1": {
        "total": 91,
        "ok": 91,
        "ko": 0
    },
    "percentiles2": {
        "total": 91,
        "ok": 91,
        "ko": 0
    },
    "percentiles3": {
        "total": 91,
        "ok": 91,
        "ko": 0
    },
    "percentiles4": {
        "total": 91,
        "ok": 91,
        "ko": 0
    },
    "group1": {
        "name": "t < 800 ms",
        "count": 1,
        "percentage": 100
    },
    "group2": {
        "name": "800 ms < t < 1200 ms",
        "count": 0,
        "percentage": 0
    },
    "group3": {
        "name": "t > 1200 ms",
        "count": 0,
        "percentage": 0
    },
    "group4": {
        "name": "failed",
        "count": 0,
        "percentage": 0
    },
    "meanNumberOfRequestsPerSecond": {
        "total": 0.5,
        "ok": 0.5,
        "ko": 0
    }
}
    },"req_application-css-083e9": {
        "type": "REQUEST",
        "name": "application.css Redirect 2",
"path": "application.css Redirect 2",
"pathFormatted": "req_application-css-083e9",
"stats": {
    "name": "application.css Redirect 2",
    "numberOfRequests": {
        "total": 1,
        "ok": 1,
        "ko": 0
    },
    "minResponseTime": {
        "total": 85,
        "ok": 85,
        "ko": 0
    },
    "maxResponseTime": {
        "total": 85,
        "ok": 85,
        "ko": 0
    },
    "meanResponseTime": {
        "total": 85,
        "ok": 85,
        "ko": 0
    },
    "standardDeviation": {
        "total": 0,
        "ok": 0,
        "ko": 0
    },
    "percentiles1": {
        "total": 85,
        "ok": 85,
        "ko": 0
    },
    "percentiles2": {
        "total": 85,
        "ok": 85,
        "ko": 0
    },
    "percentiles3": {
        "total": 85,
        "ok": 85,
        "ko": 0
    },
    "percentiles4": {
        "total": 85,
        "ok": 85,
        "ko": 0
    },
    "group1": {
        "name": "t < 800 ms",
        "count": 1,
        "percentage": 100
    },
    "group2": {
        "name": "800 ms < t < 1200 ms",
        "count": 0,
        "percentage": 0
    },
    "group3": {
        "name": "t > 1200 ms",
        "count": 0,
        "percentage": 0
    },
    "group4": {
        "name": "failed",
        "count": 0,
        "percentage": 0
    },
    "meanNumberOfRequestsPerSecond": {
        "total": 0.5,
        "ok": 0.5,
        "ko": 0
    }
}
    },"req_gov-uk-logotype-4809f": {
        "type": "REQUEST",
        "name": "gov.uk_logotype_crown_invert_trans.png?0.19.2 Redirect 2",
"path": "gov.uk_logotype_crown_invert_trans.png?0.19.2 Redirect 2",
"pathFormatted": "req_gov-uk-logotype-4809f",
"stats": {
    "name": "gov.uk_logotype_crown_invert_trans.png?0.19.2 Redirect 2",
    "numberOfRequests": {
        "total": 1,
        "ok": 1,
        "ko": 0
    },
    "minResponseTime": {
        "total": 146,
        "ok": 146,
        "ko": 0
    },
    "maxResponseTime": {
        "total": 146,
        "ok": 146,
        "ko": 0
    },
    "meanResponseTime": {
        "total": 146,
        "ok": 146,
        "ko": 0
    },
    "standardDeviation": {
        "total": 0,
        "ok": 0,
        "ko": 0
    },
    "percentiles1": {
        "total": 146,
        "ok": 146,
        "ko": 0
    },
    "percentiles2": {
        "total": 146,
        "ok": 146,
        "ko": 0
    },
    "percentiles3": {
        "total": 146,
        "ok": 146,
        "ko": 0
    },
    "percentiles4": {
        "total": 146,
        "ok": 146,
        "ko": 0
    },
    "group1": {
        "name": "t < 800 ms",
        "count": 1,
        "percentage": 100
    },
    "group2": {
        "name": "800 ms < t < 1200 ms",
        "count": 0,
        "percentage": 0
    },
    "group3": {
        "name": "t > 1200 ms",
        "count": 0,
        "percentage": 0
    },
    "group4": {
        "name": "failed",
        "count": 0,
        "percentage": 0
    },
    "meanNumberOfRequestsPerSecond": {
        "total": 0.5,
        "ok": 0.5,
        "ko": 0
    }
}
    },"req_govuk-template--00a53": {
        "type": "REQUEST",
        "name": "govuk-template.js?0.19.2 Redirect 2",
"path": "govuk-template.js?0.19.2 Redirect 2",
"pathFormatted": "req_govuk-template--00a53",
"stats": {
    "name": "govuk-template.js?0.19.2 Redirect 2",
    "numberOfRequests": {
        "total": 1,
        "ok": 1,
        "ko": 0
    },
    "minResponseTime": {
        "total": 29,
        "ok": 29,
        "ko": 0
    },
    "maxResponseTime": {
        "total": 29,
        "ok": 29,
        "ko": 0
    },
    "meanResponseTime": {
        "total": 29,
        "ok": 29,
        "ko": 0
    },
    "standardDeviation": {
        "total": 0,
        "ok": 0,
        "ko": 0
    },
    "percentiles1": {
        "total": 29,
        "ok": 29,
        "ko": 0
    },
    "percentiles2": {
        "total": 29,
        "ok": 29,
        "ko": 0
    },
    "percentiles3": {
        "total": 29,
        "ok": 29,
        "ko": 0
    },
    "percentiles4": {
        "total": 29,
        "ok": 29,
        "ko": 0
    },
    "group1": {
        "name": "t < 800 ms",
        "count": 1,
        "percentage": 100
    },
    "group2": {
        "name": "800 ms < t < 1200 ms",
        "count": 0,
        "percentage": 0
    },
    "group3": {
        "name": "t > 1200 ms",
        "count": 0,
        "percentage": 0
    },
    "group4": {
        "name": "failed",
        "count": 0,
        "percentage": 0
    },
    "meanNumberOfRequestsPerSecond": {
        "total": 0.5,
        "ok": 0.5,
        "ko": 0
    }
}
    },"req_details-polyfil-69fcc": {
        "type": "REQUEST",
        "name": "details.polyfill.js Redirect 2",
"path": "details.polyfill.js Redirect 2",
"pathFormatted": "req_details-polyfil-69fcc",
"stats": {
    "name": "details.polyfill.js Redirect 2",
    "numberOfRequests": {
        "total": 1,
        "ok": 1,
        "ko": 0
    },
    "minResponseTime": {
        "total": 133,
        "ok": 133,
        "ko": 0
    },
    "maxResponseTime": {
        "total": 133,
        "ok": 133,
        "ko": 0
    },
    "meanResponseTime": {
        "total": 133,
        "ok": 133,
        "ko": 0
    },
    "standardDeviation": {
        "total": 0,
        "ok": 0,
        "ko": 0
    },
    "percentiles1": {
        "total": 133,
        "ok": 133,
        "ko": 0
    },
    "percentiles2": {
        "total": 133,
        "ok": 133,
        "ko": 0
    },
    "percentiles3": {
        "total": 133,
        "ok": 133,
        "ko": 0
    },
    "percentiles4": {
        "total": 133,
        "ok": 133,
        "ko": 0
    },
    "group1": {
        "name": "t < 800 ms",
        "count": 1,
        "percentage": 100
    },
    "group2": {
        "name": "800 ms < t < 1200 ms",
        "count": 0,
        "percentage": 0
    },
    "group3": {
        "name": "t > 1200 ms",
        "count": 0,
        "percentage": 0
    },
    "group4": {
        "name": "failed",
        "count": 0,
        "percentage": 0
    },
    "meanNumberOfRequestsPerSecond": {
        "total": 0.5,
        "ok": 0.5,
        "ko": 0
    }
}
    },"req_jquery-1-11-3-j-da863": {
        "type": "REQUEST",
        "name": "jquery-1.11.3.js Redirect 2",
"path": "jquery-1.11.3.js Redirect 2",
"pathFormatted": "req_jquery-1-11-3-j-da863",
"stats": {
    "name": "jquery-1.11.3.js Redirect 2",
    "numberOfRequests": {
        "total": 1,
        "ok": 1,
        "ko": 0
    },
    "minResponseTime": {
        "total": 134,
        "ok": 134,
        "ko": 0
    },
    "maxResponseTime": {
        "total": 134,
        "ok": 134,
        "ko": 0
    },
    "meanResponseTime": {
        "total": 134,
        "ok": 134,
        "ko": 0
    },
    "standardDeviation": {
        "total": 0,
        "ok": 0,
        "ko": 0
    },
    "percentiles1": {
        "total": 134,
        "ok": 134,
        "ko": 0
    },
    "percentiles2": {
        "total": 134,
        "ok": 134,
        "ko": 0
    },
    "percentiles3": {
        "total": 134,
        "ok": 134,
        "ko": 0
    },
    "percentiles4": {
        "total": 134,
        "ok": 134,
        "ko": 0
    },
    "group1": {
        "name": "t < 800 ms",
        "count": 1,
        "percentage": 100
    },
    "group2": {
        "name": "800 ms < t < 1200 ms",
        "count": 0,
        "percentage": 0
    },
    "group3": {
        "name": "t > 1200 ms",
        "count": 0,
        "percentage": 0
    },
    "group4": {
        "name": "failed",
        "count": 0,
        "percentage": 0
    },
    "meanNumberOfRequestsPerSecond": {
        "total": 0.5,
        "ok": 0.5,
        "ko": 0
    }
}
    },"req_selection-butto-bcbf8": {
        "type": "REQUEST",
        "name": "selection-buttons.js Redirect 2",
"path": "selection-buttons.js Redirect 2",
"pathFormatted": "req_selection-butto-bcbf8",
"stats": {
    "name": "selection-buttons.js Redirect 2",
    "numberOfRequests": {
        "total": 1,
        "ok": 1,
        "ko": 0
    },
    "minResponseTime": {
        "total": 39,
        "ok": 39,
        "ko": 0
    },
    "maxResponseTime": {
        "total": 39,
        "ok": 39,
        "ko": 0
    },
    "meanResponseTime": {
        "total": 39,
        "ok": 39,
        "ko": 0
    },
    "standardDeviation": {
        "total": 0,
        "ok": 0,
        "ko": 0
    },
    "percentiles1": {
        "total": 39,
        "ok": 39,
        "ko": 0
    },
    "percentiles2": {
        "total": 39,
        "ok": 39,
        "ko": 0
    },
    "percentiles3": {
        "total": 39,
        "ok": 39,
        "ko": 0
    },
    "percentiles4": {
        "total": 39,
        "ok": 39,
        "ko": 0
    },
    "group1": {
        "name": "t < 800 ms",
        "count": 1,
        "percentage": 100
    },
    "group2": {
        "name": "800 ms < t < 1200 ms",
        "count": 0,
        "percentage": 0
    },
    "group3": {
        "name": "t > 1200 ms",
        "count": 0,
        "percentage": 0
    },
    "group4": {
        "name": "failed",
        "count": 0,
        "percentage": 0
    },
    "meanNumberOfRequestsPerSecond": {
        "total": 0.5,
        "ok": 0.5,
        "ko": 0
    }
}
    },"req_shim-links-with-8a39f": {
        "type": "REQUEST",
        "name": "shim-links-with-button-role.js Redirect 2",
"path": "shim-links-with-button-role.js Redirect 2",
"pathFormatted": "req_shim-links-with-8a39f",
"stats": {
    "name": "shim-links-with-button-role.js Redirect 2",
    "numberOfRequests": {
        "total": 1,
        "ok": 1,
        "ko": 0
    },
    "minResponseTime": {
        "total": 51,
        "ok": 51,
        "ko": 0
    },
    "maxResponseTime": {
        "total": 51,
        "ok": 51,
        "ko": 0
    },
    "meanResponseTime": {
        "total": 51,
        "ok": 51,
        "ko": 0
    },
    "standardDeviation": {
        "total": 0,
        "ok": 0,
        "ko": 0
    },
    "percentiles1": {
        "total": 51,
        "ok": 51,
        "ko": 0
    },
    "percentiles2": {
        "total": 51,
        "ok": 51,
        "ko": 0
    },
    "percentiles3": {
        "total": 51,
        "ok": 51,
        "ko": 0
    },
    "percentiles4": {
        "total": 51,
        "ok": 51,
        "ko": 0
    },
    "group1": {
        "name": "t < 800 ms",
        "count": 1,
        "percentage": 100
    },
    "group2": {
        "name": "800 ms < t < 1200 ms",
        "count": 0,
        "percentage": 0
    },
    "group3": {
        "name": "t > 1200 ms",
        "count": 0,
        "percentage": 0
    },
    "group4": {
        "name": "failed",
        "count": 0,
        "percentage": 0
    },
    "meanNumberOfRequestsPerSecond": {
        "total": 0.5,
        "ok": 0.5,
        "ko": 0
    }
}
    },"req_show-hide-conte-637cc": {
        "type": "REQUEST",
        "name": "show-hide-content.js Redirect 2",
"path": "show-hide-content.js Redirect 2",
"pathFormatted": "req_show-hide-conte-637cc",
"stats": {
    "name": "show-hide-content.js Redirect 2",
    "numberOfRequests": {
        "total": 1,
        "ok": 1,
        "ko": 0
    },
    "minResponseTime": {
        "total": 18,
        "ok": 18,
        "ko": 0
    },
    "maxResponseTime": {
        "total": 18,
        "ok": 18,
        "ko": 0
    },
    "meanResponseTime": {
        "total": 18,
        "ok": 18,
        "ko": 0
    },
    "standardDeviation": {
        "total": 0,
        "ok": 0,
        "ko": 0
    },
    "percentiles1": {
        "total": 18,
        "ok": 18,
        "ko": 0
    },
    "percentiles2": {
        "total": 18,
        "ok": 18,
        "ko": 0
    },
    "percentiles3": {
        "total": 18,
        "ok": 18,
        "ko": 0
    },
    "percentiles4": {
        "total": 18,
        "ok": 18,
        "ko": 0
    },
    "group1": {
        "name": "t < 800 ms",
        "count": 1,
        "percentage": 100
    },
    "group2": {
        "name": "800 ms < t < 1200 ms",
        "count": 0,
        "percentage": 0
    },
    "group3": {
        "name": "t > 1200 ms",
        "count": 0,
        "percentage": 0
    },
    "group4": {
        "name": "failed",
        "count": 0,
        "percentage": 0
    },
    "meanNumberOfRequestsPerSecond": {
        "total": 0.5,
        "ok": 0.5,
        "ko": 0
    }
}
    },"req_application-js--9753b": {
        "type": "REQUEST",
        "name": "application.js Redirect 2",
"path": "application.js Redirect 2",
"pathFormatted": "req_application-js--9753b",
"stats": {
    "name": "application.js Redirect 2",
    "numberOfRequests": {
        "total": 1,
        "ok": 1,
        "ko": 0
    },
    "minResponseTime": {
        "total": 73,
        "ok": 73,
        "ko": 0
    },
    "maxResponseTime": {
        "total": 73,
        "ok": 73,
        "ko": 0
    },
    "meanResponseTime": {
        "total": 73,
        "ok": 73,
        "ko": 0
    },
    "standardDeviation": {
        "total": 0,
        "ok": 0,
        "ko": 0
    },
    "percentiles1": {
        "total": 73,
        "ok": 73,
        "ko": 0
    },
    "percentiles2": {
        "total": 73,
        "ok": 73,
        "ko": 0
    },
    "percentiles3": {
        "total": 73,
        "ok": 73,
        "ko": 0
    },
    "percentiles4": {
        "total": 73,
        "ok": 73,
        "ko": 0
    },
    "group1": {
        "name": "t < 800 ms",
        "count": 1,
        "percentage": 100
    },
    "group2": {
        "name": "800 ms < t < 1200 ms",
        "count": 0,
        "percentage": 0
    },
    "group3": {
        "name": "t > 1200 ms",
        "count": 0,
        "percentage": 0
    },
    "group4": {
        "name": "failed",
        "count": 0,
        "percentage": 0
    },
    "meanNumberOfRequestsPerSecond": {
        "total": 0.5,
        "ok": 0.5,
        "ko": 0
    }
}
    }
}

}